minchoc/__init__.py
minchoc/admin.py
minchoc/apps.py
minchoc/constants.py
minchoc/filterlex.py
minchoc/filteryacc.py
minchoc/migrations/0001_initial.py
minchoc/migrations/0002_alter_company_options_alter_package_unique_together_and_more.py
minchoc/migrations/__init__.py
minchoc/models.py
minchoc/parsetab.py
minchoc/py.typed
minchoc/urls.py
minchoc/utils.py
minchoc/views.py
minchoc/wsgi.py
minchoc-0.1.0.dist-info/METADATA
minchoc-0.1.0.dist-info/WHEEL
minchoc-0.1.0.dist-info/licenses/LICENSE.txt
minchoc-0.1.0.dist-info/RECORD
