Metadata-Version: 2.4
Name: minchoc
Version: 0.1.0
Summary: Minimal Chocolatey-compatible NuGet server in a Django app.
License-Expression: MIT
License-File: LICENSE.txt
Keywords: chocolatey,django,windows
Author: Andrew Udvare
Author-email: audvare@gmail.com
Requires-Python: >=3.10,<4.0
Classifier: Development Status :: 4 - Beta
Classifier: Intended Audience :: Developers
Classifier: Programming Language :: Python
Classifier: Programming Language :: Python :: 3.10
Classifier: Programming Language :: Python :: 3.11
Classifier: Programming Language :: Python :: 3.12
Classifier: Programming Language :: Python :: 3.13
Classifier: Programming Language :: Python :: 3.14
Classifier: Typing :: Typed
Classifier: Environment :: Web Environment
Classifier: Intended Audience :: Information Technology
Classifier: Framework :: Django
Classifier: Intended Audience :: System Administrators
Classifier: Topic :: System :: Software Distribution
Requires-Dist: defusedxml (>=0.7.1,<0.8.0)
Requires-Dist: django (>=5.2.8,<6.0.0)
Requires-Dist: django-stubs-ext (>=5.2.7,<6.0.0)
Requires-Dist: ply (>=3.11,<4.0)
Requires-Dist: typing-extensions (>=4.15.0,<5.0.0)
Project-URL: Documentation, https://minchoc.readthedocs.org
Project-URL: Homepage, https://tatsh.github.io/minchoc/
Project-URL: Issues, https://github.com/Tatsh/minchoc/issues
Project-URL: Repository, https://github.com/Tatsh/minchoc
